jsonl2json_aq/__init__.py
jsonl2json_aq/__main__.py
jsonl2json_aq-0.1.1.dist-info/LICENSE.md
jsonl2json_aq-0.1.1.dist-info/entry_points.txt
jsonl2json_aq-0.1.1.dist-info/WHEEL
jsonl2json_aq-0.1.1.dist-info/METADATA
jsonl2json_aq-0.1.1.dist-info/RECORD
