Metadata-Version: 2.1
Name: jsonl2json-aq
Version: 0.1.1
Summary: Converts jsonlines file to json file, by converting it into array of json objects.
Home-page: https://github.com/aqdasak/jsonl2json
License: MIT
Keywords: python,jsonl to json,ndjson to json,convert jsonlines to json
Author: Aqdas Ahmad Khan
Author-email: aqdasak@gmail.com
Requires-Python: >=3.10,<4.0
Classifier: License :: OSI Approved :: MIT License
Classifier: Programming Language :: Python :: 3
Classifier: Programming Language :: Python :: 3.10
Classifier: Programming Language :: Python :: 3.11
Requires-Dist: jsonlines (>=4.0.0,<5.0.0)
Project-URL: Repository, https://github.com/aqdasak/jsonl2json
